MANIFEST.in
README.rst
setup.py
notify_run_server/__init__.py
notify_run_server/app.py
notify_run_server/model.py
notify_run_server/model_dynamodb.py
notify_run_server/model_sqlalchemy.py
notify_run_server/notify.py
notify_run_server/params.py
notify_run_server.egg-info/PKG-INFO
notify_run_server.egg-info/SOURCES.txt
notify_run_server.egg-info/dependency_links.txt
notify_run_server.egg-info/entry_points.txt
notify_run_server.egg-info/requires.txt
notify_run_server.egg-info/top_level.txt