Metadata-Version: 1.2
Name: notify-run-server
Version: 0.0.7
Summary: Server for self-hosted notify.run server.
Home-page: https://notify.run/
Author: Paul Butler
Author-email: notify@paulbutler.org
License: UNKNOWN
Platform: UNKNOWN
Requires-Python: >=2.7
